LICENSE.txt
MANIFEST.in
README.rst
setup.py
djmodelcron/__init__.py
djmodelcron/admin.py
djmodelcron/models.py
djmodelcron/tasks.py
djmodelcron.egg-info/PKG-INFO
djmodelcron.egg-info/SOURCES.txt
djmodelcron.egg-info/dependency_links.txt
djmodelcron.egg-info/requires.txt
djmodelcron.egg-info/top_level.txt
djmodelcron/migrations/0001_initial.py
djmodelcron/migrations/__init__.py