Metadata-Version: 1.1
Name: djmodelcron
Version: 0.1.0
Summary: Generic cron task for running instances of django models
Home-page: https://github.com/josesanch/djmodelcron
Author: José Sánchez Moreno
Author-email: jose@o2w.es
License: MIT
Platform: All platforms
Classifier: Development Status :: 4 - Beta
Classifier: Intended Audience :: Developers
Classifier: License :: OSI Approved :: Python Software Foundation License
Classifier: Operating System :: MacOS :: MacOS X
Classifier: Operating System :: Microsoft :: Windows
Classifier: Operating System :: POSIX
Classifier: Programming Language :: Python
Classifier: Programming Language :: SQL
